{
  "session_id": "7b77d439-e26e-4adf-9100-8d6203291fd2",
  "project_path": "/",
  "start_time": "2026-02-24T04:32:07.212Z",
  "duration_minutes": 822,
  "user_message_count": 5,
  "assistant_message_count": 11,
  "tool_counts": {
    "Glob": 2
  },
  "languages": {},
  "git_commits": 0,
  "git_pushes": 0,
  "input_tokens": 33,
  "output_tokens": 62,
  "first_prompt": "Here are a handful of OKR concepts I'm considering setting for myself for the first half of 2026. Help me sharpen/refine these in light of my role proposal I've pitched to Kari and the active AEF and…",
  "user_interruptions": 0,
  "user_response_times": [
    321.621,
    28.886,
    1563.837
  ],
  "tool_errors": 1,
  "tool_error_categories": {
    "Other": 1
  },
  "uses_task_agent": false,
  "uses_mcp": false,
  "uses_web_search": false,
  "uses_web_fetch": false,
  "lines_added": 0,
  "lines_removed": 0,
  "files_modified": 0,
  "message_hours": [
    23,
    23,
    23,
    0,
    13
  ],
  "user_message_timestamps": [
    "2026-02-24T04:32:09.243Z",
    "2026-02-24T04:39:27.805Z",
    "2026-02-24T04:40:07.106Z",
    "2026-02-24T05:06:39.041Z",
    "2026-02-24T18:13:32.722Z"
  ]
}